{
  "nodes": [
{"id": ".net", "color": 45.99548297669578, "group":0},
{"id": "3d", "color": 16.66233161547933, "group":0},
{"id": "abap", "color": 16.719112496754907, "group":0},
{"id": "ado", "color": 15.17296969575045, "group":0},
{"id": "adobe", "color": 20.629634018753727, "group":0},
{"id": "adwords", "color": 15.997885488783538, "group":0},
{"id": "agile", "color": 43.03715134177, "group":0},
{"id": "ajax", "color": 31.48915657355782, "group":0},
{"id": "algorithms", "color": 19.268398307831852, "group":0},
{"id": "analysts", "color": 15.369457010403995, "group":0},
{"id": "android", "color": 29.511885452558154, "group":0},
{"id": "angularjs", "color": 26.216413568723155, "group":0},
{"id": "ansible", "color": 15.098648554283358, "group":0},
{"id": "antivirus", "color": 20.944346096398796, "group":0},
{"id": "apache", "color": 18.70334620182988, "group":0},
{"id": "apex", "color": 15.015448700138636, "group":0},
{"id": "apps", "color": 57.88766717563106, "group":0},
{"id": "architecture", "color": 39.11047404490175, "group":0},
{"id": "artificial", "color": 15.369457010403995, "group":0},
{"id": "asp", "color": 36.252490842185225, "group":0},
{"id": "assembly", "color": 22.568511627940946, "group":0},
{"id": "autocad", "color": 18.11079551155531, "group":0},
{"id": "automation", "color": 46.78160276609856, "group":0},
{"id": "aws", "color": 21.622101615909855, "group":0},
{"id": "azure", "color": 17.67951486597909, "group":0},
{"id": "basic", "color": 16.89806721752921, "group":0},
{"id": "bba", "color": 16.12169377464654, "group":0},
{"id": "bca", "color": 15.742125960706082, "group":0},
{"id": "bcom", "color": 16.349433079796388, "group":0},
{"id": "bde", "color": 15.81077068351414, "group":0},
{"id": "bdm", "color": 16.448653395441, "group":0},
{"id": "bi", "color": 15.920271803511636, "group":0},
{"id": "big", "color": 20.044742015547342, "group":0},
{"id": "bootstrap", "color": 19.389976380943427, "group":0},
{"id": "bpo", "color": 56.832105805791414, "group":0},
{"id": "bsc", "color": 15.742125960706082, "group":0},
{"id": "btech", "color": 15.192719111058901, "group":0},
{"id": "c", "color": 63.57245302967359, "group":0},
{"id": "cakephp", "color": 15.116550050167783, "group":0},
{"id": "calls", "color": 26.8123986488045, "group":0},
{"id": "cases", "color": 22.369819869112753, "group":0},
{"id": "cassandra", "color": 15.21295957544762, "group":0},
{"id": "cce", "color": 23.19472290579494, "group":0},
{"id": "ccna", "color": 15.321965748772929, "group":0},
{"id": "chain", "color": 23.868815529041182, "group":0},
{"id": "cisco", "color": 16.25496868544505, "group":0},
{"id": "cms", "color": 19.034019332558778, "group":0},
{"id": "cocoa", "color": 15.047507999617597, "group":0},
{"id": "codeigniter", "color": 15.369457010403995, "group":0},
{"id": "coding", "color": 37.35375406366099, "group":0},
{"id": "cold", "color": 25.37556915395178, "group":0},
{"id": "com", "color": 19.90727882950125, "group":0},
{"id": "comp", "color": 17.9319038399881, "group":0},
{"id": "corel", "color": 16.552869074842924, "group":0},
{"id": "cse", "color": 16.30162090270686, "group":0},
{"id": "csr", "color": 16.552869074842924, "group":0},
{"id": "css", "color": 49.259194593618254, "group":0},
{"id": "cv", "color": 16.552869074842924, "group":0},
{"id": "cvs", "color": 15.116550050167783, "group":0},
{"id": "d", "color": 20.330007015789164, "group":0},
{"id": "data", "color": 66.04917195370385, "group":0},
{"id": "database", "color": 36.79636106358998, "group":0},
{"id": "dba", "color": 15.233703298351438, "group":0},
{"id": "debugging", "color": 27.763105871458507, "group":0},
{"id": "design", "color": 68.6505842116524, "group":0},
{"id": "desktop", "color": 16.20944828650217, "group":0},
{"id": "devops", "color": 16.777305176764347, "group":0},
{"id": "django", "color": 15.742125960706082, "group":0},
{"id": "dns", "color": 17.024909165597094, "group":0},
{"id": "docker", "color": 15.614549829109276, "group":0},
{"id": "dot", "color": 15.526764388746228, "group":0},
{"id": "dreamweaver", "color": 15.031281516458732, "group":0},
{"id": "drupal", "color": 16.552869074842924, "group":0},
{"id": "e", "color": 27.438389300321447, "group":0},
{"id": "e-commerce", "color": 16.39843405793236, "group":0},
{"id": "eclipse", "color": 16.16503224710386, "group":0},
{"id": "ejb", "color": 15.015448700138636, "group":0},
{"id": "email", "color": 34.205794520625794, "group":0},
{"id": "embedded", "color": 18.496051834434585, "group":0},
{"id": "erp", "color": 30.273784949508816, "group":0},
{"id": "etl", "color": 15.88287140581402, "group":0},
{"id": "facebook", "color": 15.88287140581402, "group":0},
{"id": "fico", "color": 15.21295957544762, "group":0},
{"id": "firewall", "color": 15.299080711605312, "group":0},
{"id": "firmware", "color": 15.081181362322036, "group":0},
{"id": "flex", "color": 15.192719111058901, "group":0},
{"id": "fresher", "color": 35.20401440303813, "group":0},
{"id": "gaap", "color": 15.27675088286756, "group":0},
{"id": "git", "color": 28.09589618914013, "group":0},
{"id": "google", "color": 20.47798090728333, "group":0},
{"id": "graphic", "color": 20.785057830254672, "group":0},
{"id": "graphics", "color": 21.446370484715345, "group":0},
{"id": "gst", "color": 17.44505328535932, "group":0},
{"id": "hadoop", "color": 16.777305176764347, "group":0},
{"id": "hardware", "color": 21.10759490291162, "group":0},
{"id": "hibernate", "color": 31.914591343832733, "group":0},
{"id": "hive", "color": 15.0, "group":0},
{"id": "hr", "color": 50.12646324554235, "group":0},
{"id": "html", "color": 60.07817885431136, "group":0},
{"id": "ibm", "color": 15.098648554283358, "group":0},
{"id": "ifrs", "color": 15.047507999617597, "group":0},
{"id": "illustrator", "color": 25.108776041818253, "group":0},
{"id": "internet", "color": 19.514577368913464, "group":0},
{"id": "ios", "color": 22.369819869112753, "group":0},
{"id": "iphone", "color": 15.645278684313178, "group":0},
{"id": "ites", "color": 17.227245700845916, "group":0},
{"id": "j2ee", "color": 32.79745790131716, "group":0},
{"id": "java", "color": 58.96947400295527, "group":0},
{"id": "javascript", "color": 67.33390627798241, "group":0},
{"id": "jboss", "color": 16.20944828650217, "group":0},
{"id": "jdbc", "color": 15.88287140581402, "group":0},
{"id": "jenkins", "color": 16.836944758444066, "group":0},
{"id": "jms", "color": 15.584566479334285, "group":0},
{"id": "joomla", "color": 15.70904751682251, "group":0},
{"id": "jquery", "color": 51.92622796304219, "group":0},
{"id": "json", "color": 30.669000743229258, "group":0},
{"id": "jsp", "color": 18.298693695214595, "group":0},
{"id": "junit", "color": 15.27675088286756, "group":0},
{"id": "kpo", "color": 17.090705168066364, "group":0},
{"id": "lan", "color": 15.555310548458758, "group":0},
{"id": "laravel", "color": 15.614549829109276, "group":0},
{"id": "linq", "color": 15.776026866378619, "group":0},
{"id": "linux", "color": 48.41296653966126, "group":0},
{"id": "machine", "color": 25.929220930739316, "group":0},
{"id": "magento", "color": 15.419339275587102, "group":0},
{"id": "maven", "color": 18.020251340499684, "group":0},
{"id": "mca", "color": 16.66233161547933, "group":0},
{"id": "microservices", "color": 15.394091882503828, "group":0},
{"id": "microsoft", "color": 29.511885452558154, "group":0},
{"id": "mining", "color": 17.52129574309656, "group":0},
{"id": "mis", "color": 33.25542225050228, "group":0},
{"id": "mm", "color": 15.098648554283358, "group":0},
{"id": "mobile", "color": 28.78650603738049, "group":0},
{"id": "modeling", "color": 25.108776041818253, "group":0},
{"id": "mongodb", "color": 18.496051834434585, "group":0},
{"id": "ms", "color": 52.859809681081856, "group":0},
{"id": "mvc", "color": 39.72540510538397, "group":0},
{"id": "mysql", "color": 51.01529564845453, "group":0},
{"id": "net", "color": 53.81660395690296, "group":0},
{"id": "network", "color": 27.121550600489208, "group":0},
{"id": "networking", "color": 44.47999629421621, "group":0},
{"id": "node.js", "color": 21.986780644707377, "group":0},
{"id": "nosql", "color": 19.034019332558778, "group":0},
{"id": "objectoriented", "color": 20.185623083592667, "group":0},
{"id": "objective", "color": 15.70904751682251, "group":0},
{"id": "office", "color": 55.80215315865046, "group":0},
{"id": "online", "color": 24.1047782869665, "group":0},
{"id": "ooad", "color": 15.081181362322036, "group":0},
{"id": "oracle", "color": 47.587268622741135, "group":0},
{"id": "perl", "color": 22.980838784472645, "group":0},
{"id": "photoshop", "color": 29.888157391921958, "group":0},
{"id": "php", "color": 45.22843505205611, "group":0},
{"id": "pl", "color": 17.158137121068503, "group":0},
{"id": "plsql", "color": 17.599433891828404, "group":0},
{"id": "pmp", "color": 23.413925037773147, "group":0},
{"id": "postgresql", "color": 15.614549829109276, "group":0},
{"id": "power", "color": 18.496051834434585, "group":0},
{"id": "powerpoint", "color": 16.960709424254905, "group":0},
{"id": "ppc", "color": 16.500121385586183, "group":0},
{"id": "pr", "color": 15.015448700138636, "group":0},
{"id": "profiling", "color": 24.84845553376229, "group":0},
{"id": "programming", "color": 34.69877572427544, "group":0},
{"id": "protocols", "color": 15.233703298351438, "group":0},
{"id": "python", "color": 43.74971523061762, "group":0},
{"id": "qa", "color": 19.14976981136217, "group":0},
{"id": "qc", "color": 15.445214419363701, "group":0},
{"id": "queries", "color": 15.81077068351414, "group":0},
{"id": "r", "color": 17.52129574309656, "group":0},
{"id": "react.js", "color": 19.642276433438543, "group":0},
{"id": "regression", "color": 15.846378370246953, "group":0},
{"id": "relations", "color": 18.598426299769184, "group":0},
{"id": "resources", "color": 15.471732922214722, "group":0},
{"id": "rest", "color": 26.510746958903383, "group":0},
{"id": "returns", "color": 15.081181362322036, "group":0},
{"id": "routing", "color": 15.031281516458732, "group":0},
{"id": "sales", "color": 70.0, "group":0},
{"id": "salesforce", "color": 17.9319038399881, "group":0},
{"id": "sap", "color": 38.51046168024969, "group":0},
{"id": "sas", "color": 18.396161051592628, "group":0},
{"id": "scala", "color": 15.676771581178558, "group":0},
{"id": "scripting", "color": 24.34660801834122, "group":0},
{"id": "scrum", "color": 21.802202122551662, "group":0},
{"id": "sdk", "color": 17.67951486597909, "group":0},
{"id": "security", "color": 32.35060411600762, "group":0},
{"id": "selenium", "color": 21.27490272459226, "group":0},
{"id": "sem", "color": 17.29807259501432, "group":0},
{"id": "seo", "color": 29.144742156994525, "group":0},
{"id": "server", "color": 42.34187479552128, "group":0},
{"id": "servlets", "color": 15.254962792780344, "group":0},
{"id": "sheet", "color": 17.9319038399881, "group":0},
{"id": "shell", "color": 20.044742015547342, "group":0},
{"id": "sixsigma", "color": 25.648995804865493, "group":0},
{"id": "soap", "color": 17.3706605277095, "group":0},
{"id": "soc", "color": 15.95860212397426, "group":0},
{"id": "social", "color": 40.35562579986098, "group":0},
{"id": "software", "color": 61.214450521648715, "group":0},
{"id": "sourcing", "color": 24.594450599479742, "group":0},
{"id": "spark", "color": 16.038145594415674, "group":0},
{"id": "spot", "color": 15.134896648499652, "group":0},
{"id": "spring", "color": 33.72477341640823, "group":0},
{"id": "sql", "color": 62.37897442574668, "group":0},
{"id": "sqlite", "color": 15.21295957544762, "group":0},
{"id": "ssis", "color": 15.81077068351414, "group":0},
{"id": "ssrs", "color": 16.12169377464654, "group":0},
{"id": "statements", "color": 15.742125960706082, "group":0},
{"id": "statistics", "color": 16.606928281625176, "group":0},
{"id": "structures", "color": 24.594450599479742, "group":0},
{"id": "struts", "color": 18.020251340499684, "group":0},
{"id": "studio", "color": 17.76158697192225, "group":0},
{"id": "suite", "color": 15.21295957544762, "group":0},
{"id": "svn", "color": 15.153699416297615, "group":0},
{"id": "swift", "color": 15.345419799062073, "group":0},
{"id": "system", "color": 41.66346618777479, "group":0},
{"id": "systems", "color": 22.175948523668122, "group":0},
{"id": "t", "color": 15.031281516458732, "group":0},
{"id": "tableau", "color": 15.21295957544762, "group":0},
{"id": "tally", "color": 20.47798090728333, "group":0},
{"id": "tds", "color": 18.203590971128886, "group":0},
{"id": "to", "color": 15.299080711605312, "group":0},
{"id": "tomcat", "color": 16.836944758444066, "group":0},
{"id": "troubleshooting", "color": 37.92500607250551, "group":0},
{"id": "ui", "color": 28.436960998844246, "group":0},
{"id": "uk", "color": 18.81087483030622, "group":0},
{"id": "uml", "color": 15.27675088286756, "group":0},
{"id": "unix", "color": 31.074043174801094, "group":0},
{"id": "ux", "color": 18.921077048521333, "group":0},
{"id": "vb", "color": 17.84569971712026, "group":0},
{"id": "vb.net", "color": 15.49891078060775, "group":0},
{"id": "verilog", "color": 15.17296969575045, "group":0},
{"id": "virtualization", "color": 15.742125960706082, "group":0},
{"id": "visual", "color": 22.77214365481784, "group":0},
{"id": "visualization", "color": 15.233703298351438, "group":0},
{"id": "vmware", "color": 16.349433079796388, "group":0},
{"id": "voice", "color": 54.79718794709318, "group":0},
{"id": "vpn", "color": 15.098648554283358, "group":0},
{"id": "wan", "color": 15.345419799062073, "group":0},
{"id": "warehouse", "color": 16.552869074842924, "group":0},
{"id": "warehousing", "color": 16.0794067265356, "group":0},
{"id": "wcf", "color": 19.77315060503421, "group":0},
{"id": "web", "color": 64.79560626252609, "group":0},
{"id": "weblogic", "color": 15.526764388746228, "group":0},
{"id": "website", "color": 18.298693695214595, "group":0},
{"id": "websphere", "color": 15.047507999617597, "group":0},
{"id": "windows", "color": 35.72181532653798, "group":0},
{"id": "wipro", "color": 15.064137937739897, "group":0},
{"id": "wireless", "color": 15.299080711605312, "group":0},
{"id": "word", "color": 16.89806721752921, "group":0},
{"id": "wordpress", "color": 23.63857740732138, "group":0},
{"id": "wpf", "color": 15.584566479334285, "group":0},
{"id": "xhtml", "color": 16.0794067265356, "group":0},
{"id": "xml", "color": 41.00151628949668, "group":0},
{"id": "xslt", "color": 15.254962792780344, "group":0},
{"id": "zend", "color": 15.321965748772929, "group":0}
    ],
  
  "links": [
    {"source": ".net", "target": "ado", "value": 0.20707390525507272, "group":0},
{"source": ".net", "target": "asp", "value": 2.636509000712651, "group":0},
{"source": ".net", "target": "assembly", "value": 2.7317317868432993, "group":0},
{"source": ".net", "target": "c", "value": 2.584822543793697, "group":0},
{"source": ".net", "target": "dot", "value": 1.1616752455749515, "group":0},
{"source": ".net", "target": "html", "value": 1.3920301710053087, "group":0},
{"source": ".net", "target": "javascript", "value": 1.456052559883076, "group":0},
{"source": ".net", "target": "linq", "value": 0.1612596615923551, "group":0},
{"source": ".net", "target": "mvc", "value": 1.348461010566899, "group":0},
{"source": ".net", "target": "net", "value": 3.0, "group":0},
{"source": ".net", "target": "oracle", "value": 1.3361973001104028, "group":0},
{"source": ".net", "target": "pmp", "value": 2.182883317335324, "group":0},
{"source": ".net", "target": "python", "value": 1.3058914941847952, "group":0},
{"source": ".net", "target": "server", "value": 1.023847723199927, "group":0},
{"source": ".net", "target": "sixsigma", "value": 2.236933526772084, "group":0},
{"source": ".net", "target": "sql", "value": 1.936277627440595, "group":0},
{"source": ".net", "target": "vb", "value": 0.417819586099036, "group":0},
{"source": ".net", "target": "vb.net", "value": 0.501081355362976, "group":0},
{"source": ".net", "target": "wcf", "value": 0.73526187199214, "group":0},
{"source": "3d", "target": "autocad", "value": 0.5419988451420148, "group":0},
{"source": "3d", "target": "d", "value": 2.9883907448029254, "group":0},
{"source": "abap", "target": "sap", "value": 2.2735690570534897, "group":0},
{"source": "ado", "target": "asp", "value": 1.1672172800904765, "group":0},
{"source": "ado", "target": "net", "value": 0.8651843447912624, "group":0},
{"source": "ado", "target": "wcf", "value": 0.6987393067069424, "group":0},
{"source": "adobe", "target": "graphic", "value": 0.595489267496319, "group":0},
{"source": "adobe", "target": "illustrator", "value": 1.618651971741342, "group":0},
{"source": "adobe", "target": "photoshop", "value": 1.6257118007055131, "group":0},
{"source": "adobe", "target": "suite", "value": 0.6065103349006118, "group":0},
{"source": "adwords", "target": "google", "value": 2.8856216703950928, "group":0},
{"source": "adwords", "target": "ppc", "value": 2.0186491383295344, "group":0},
{"source": "adwords", "target": "sem", "value": 2.246046905202106, "group":0},
{"source": "adwords", "target": "seo", "value": 0.8881225871923647, "group":0},
{"source": "agile", "target": "scrum", "value": 2.0951552985961177, "group":0},
{"source": "ajax", "target": "css", "value": 0.3817462420335239, "group":0},
{"source": "ajax", "target": "html", "value": 1.4430776890844357, "group":0},
{"source": "ajax", "target": "javascript", "value": 1.4110144796888537, "group":0},
{"source": "ajax", "target": "joomla", "value": 0.18378703202228608, "group":0},
{"source": "ajax", "target": "jquery", "value": 2.2828041160884545, "group":0},
{"source": "ajax", "target": "mysql", "value": 0.5145400205631498, "group":0},
{"source": "ajax", "target": "php", "value": 0.874314030964403, "group":0},
{"source": "ajax", "target": "xhtml", "value": 0.8516028386785116, "group":0},
{"source": "ajax", "target": "xml", "value": 1.0289319798104668, "group":0},
{"source": "algorithms", "target": "structures", "value": 2.1739790348458414, "group":0},
{"source": "analysts", "target": "pl", "value": 0.1288387082765789, "group":0},
{"source": "android", "target": "ios", "value": 1.0965846144672793, "group":0},
{"source": "android", "target": "json", "value": 0.1, "group":0},
{"source": "android", "target": "mobile", "value": 1.9771219732744407, "group":0},
{"source": "android", "target": "sdk", "value": 2.4348066996294118, "group":0},
{"source": "android", "target": "sqlite", "value": 0.636441505812864, "group":0},
{"source": "angularjs", "target": "bootstrap", "value": 0.7899786317988527, "group":0},
{"source": "angularjs", "target": "css", "value": 0.829265079989874, "group":0},
{"source": "angularjs", "target": "html", "value": 0.3846978340951326, "group":0},
{"source": "angularjs", "target": "javascript", "value": 0.9837749241898971, "group":0},
{"source": "angularjs", "target": "mongodb", "value": 0.24348453209784374, "group":0},
{"source": "angularjs", "target": "node.js", "value": 1.475676918220897, "group":0},
{"source": "angularjs", "target": "react.js", "value": 1.0494384356620374, "group":0},
{"source": "ansible", "target": "devops", "value": 1.4237760084218176, "group":0},
{"source": "ansible", "target": "docker", "value": 2.4153624440759196, "group":0},
{"source": "ansible", "target": "jenkins", "value": 2.1474426571274856, "group":0},
{"source": "antivirus", "target": "calls", "value": 2.2097740052053463, "group":0},
{"source": "antivirus", "target": "comp", "value": 2.4250684531688513, "group":0},
{"source": "antivirus", "target": "spot", "value": 1.0807126339157684, "group":0},
{"source": "apache", "target": "linux", "value": 0.12463647680515211, "group":0},
{"source": "apache", "target": "mysql", "value": 0.19766639584807671, "group":0},
{"source": "apache", "target": "tomcat", "value": 1.515516166793675, "group":0},
{"source": "apex", "target": "com", "value": 0.7986079144733138, "group":0},
{"source": "apex", "target": "salesforce", "value": 2.4839852524603945, "group":0},
{"source": "apps", "target": "mobile", "value": 1.2760839979023813, "group":0},
{"source": "apps", "target": "software", "value": 0.1792216022424084, "group":0},
{"source": "apps", "target": "web", "value": 0.448996789067982, "group":0},
{"source": "architecture", "target": "design", "value": 0.3700372599964824, "group":0},
{"source": "artificial", "target": "machine", "value": 1.779506639290302, "group":0},
{"source": "asp", "target": "c", "value": 2.0354537443368756, "group":0},
{"source": "asp", "target": "dot", "value": 1.195204786703362, "group":0},
{"source": "asp", "target": "javascript", "value": 0.10201580505627725, "group":0},
{"source": "asp", "target": "jquery", "value": 0.5077883743936867, "group":0},
{"source": "asp", "target": "linq", "value": 1.223660177109707, "group":0},
{"source": "asp", "target": "mvc", "value": 2.6053943523403245, "group":0},
{"source": "asp", "target": "net", "value": 2.9537930575325295, "group":0},
{"source": "asp", "target": "server", "value": 1.912094094852806, "group":0},
{"source": "asp", "target": "sql", "value": 1.8802213378146915, "group":0},
{"source": "asp", "target": "vb", "value": 1.0859857606390846, "group":0},
{"source": "asp", "target": "vb.net", "value": 1.3546234320320376, "group":0},
{"source": "asp", "target": "wcf", "value": 1.8177301512765773, "group":0},
{"source": "assembly", "target": "c", "value": 1.1506461546530156, "group":0},
{"source": "assembly", "target": "html", "value": 2.060870537700902, "group":0},
{"source": "assembly", "target": "javascript", "value": 1.7196519902432568, "group":0},
{"source": "assembly", "target": "net", "value": 2.5542195046280867, "group":0},
{"source": "assembly", "target": "oracle", "value": 2.6890595308721483, "group":0},
{"source": "assembly", "target": "pmp", "value": 2.8968895901987066, "group":0},
{"source": "assembly", "target": "python", "value": 2.6784796090622387, "group":0},
{"source": "assembly", "target": "sixsigma", "value": 2.9423367652120276, "group":0},
{"source": "assembly", "target": "sql", "value": 0.15464582883597924, "group":0},
{"source": "assembly", "target": "website", "value": 0.2047103171957333, "group":0},
{"source": "assembly", "target": "xhtml", "value": 0.8697416196516103, "group":0},
{"source": "autocad", "target": "d", "value": 0.628884113258029, "group":0},
{"source": "automation", "target": "cases", "value": 0.16570557627707924, "group":0},
{"source": "automation", "target": "selenium", "value": 1.833197883261028, "group":0},
{"source": "aws", "target": "azure", "value": 0.65555571813125, "group":0},
{"source": "aws", "target": "devops", "value": 0.7311497771836257, "group":0},
{"source": "aws", "target": "jenkins", "value": 0.12046202131046321, "group":0},
{"source": "azure", "target": "microsoft", "value": 0.3164920521656631, "group":0},
{"source": "basic", "target": "visual", "value": 0.10810348080546843, "group":0},
{"source": "bba", "target": "bca", "value": 2.4642159357224527, "group":0},
{"source": "bba", "target": "bcom", "value": 2.7858742129517573, "group":0},
{"source": "bba", "target": "bsc", "value": 1.6830411492266821, "group":0},
{"source": "bba", "target": "btech", "value": 0.3137662476598996, "group":0},
{"source": "bba", "target": "fresher", "value": 1.9281897053006865, "group":0},
{"source": "bca", "target": "bcom", "value": 0.7518472840017276, "group":0},
{"source": "bca", "target": "bsc", "value": 1.8644427894488262, "group":0},
{"source": "bca", "target": "btech", "value": 0.9303820779869867, "group":0},
{"source": "bca", "target": "fresher", "value": 1.0187802974480167, "group":0},
{"source": "bca", "target": "mca", "value": 2.077956076301313, "group":0},
{"source": "bcom", "target": "bsc", "value": 1.8023646581541948, "group":0},
{"source": "bcom", "target": "btech", "value": 0.6402390382371331, "group":0},
{"source": "bcom", "target": "fresher", "value": 1.36080632125528, "group":0},
{"source": "bde", "target": "bdm", "value": 1.5906455911844672, "group":0},
{"source": "bi", "target": "etl", "value": 0.739387624639917, "group":0},
{"source": "bi", "target": "power", "value": 1.9607029295396967, "group":0},
{"source": "bi", "target": "ssis", "value": 0.4117072442030312, "group":0},
{"source": "bi", "target": "ssrs", "value": 0.1701810731727093, "group":0},
{"source": "bi", "target": "warehousing", "value": 0.8116596155676873, "group":0},
{"source": "big", "target": "data", "value": 1.2525912732011586, "group":0},
{"source": "big", "target": "hadoop", "value": 2.156258802159452, "group":0},
{"source": "big", "target": "hive", "value": 1.1396899639925167, "group":0},
{"source": "big", "target": "scala", "value": 0.7560281231448014, "group":0},
{"source": "big", "target": "spark", "value": 2.165104228980232, "group":0},
{"source": "bootstrap", "target": "css", "value": 1.8100346671989185, "group":0},
{"source": "bootstrap", "target": "html", "value": 0.9986777914564473, "group":0},
{"source": "bootstrap", "target": "javascript", "value": 0.6594167361636172, "group":0},
{"source": "bootstrap", "target": "jquery", "value": 0.911444301834077, "group":0},
{"source": "bpo", "target": "cce", "value": 2.1386556969502686, "group":0},
{"source": "bpo", "target": "cse", "value": 0.7942861197288161, "group":0},
{"source": "bpo", "target": "csr", "value": 0.7107925935122783, "group":0},
{"source": "bpo", "target": "fresher", "value": 2.043897931366584, "group":0},
{"source": "bpo", "target": "ites", "value": 1.0340331231813535, "group":0},
{"source": "bpo", "target": "kpo", "value": 1.5630082210817204, "group":0},
{"source": "bpo", "target": "uk", "value": 1.741911625508835, "group":0},
{"source": "bpo", "target": "voice", "value": 2.8743910517703526, "group":0},
{"source": "bsc", "target": "btech", "value": 0.25098651011567896, "group":0},
{"source": "btech", "target": "mca", "value": 0.6789150390721658, "group":0},
{"source": "c", "target": "embedded", "value": 0.3556177454976347, "group":0},
{"source": "c", "target": "html", "value": 0.4270644402106505, "group":0},
{"source": "c", "target": "javascript", "value": 0.8204331590928344, "group":0},
{"source": "c", "target": "mvc", "value": 0.39660256214873835, "group":0},
{"source": "c", "target": "net", "value": 2.657424720417719, "group":0},
{"source": "c", "target": "objective", "value": 0.847105610208749, "group":0},
{"source": "c", "target": "pmp", "value": 0.5773627105353674, "group":0},
{"source": "c", "target": "python", "value": 0.34991654632171565, "group":0},
{"source": "c", "target": "server", "value": 0.28699959711696676, "group":0},
{"source": "c", "target": "sixsigma", "value": 0.3996034977302835, "group":0},
{"source": "c", "target": "sql", "value": 0.9495727087838941, "group":0},
{"source": "cakephp", "target": "codeigniter", "value": 0.9592638979454321, "group":0},
{"source": "cakephp", "target": "drupal", "value": 1.1839540716846233, "group":0},
{"source": "cakephp", "target": "joomla", "value": 0.6440491837187031, "group":0},
{"source": "cakephp", "target": "php", "value": 0.7856854033223264, "group":0},
{"source": "cakephp", "target": "wordpress", "value": 0.5918398741458114, "group":0},
{"source": "cakephp", "target": "zend", "value": 2.1211689450272218, "group":0},
{"source": "calls", "target": "comp", "value": 1.5767810852165327, "group":0},
{"source": "calls", "target": "spot", "value": 0.9887260837116871, "group":0},
{"source": "cases", "target": "regression", "value": 0.4845071205255571, "group":0},
{"source": "cases", "target": "selenium", "value": 1.1451589769810644, "group":0},
{"source": "cassandra", "target": "hadoop", "value": 0.226267424574313, "group":0},
{"source": "cassandra", "target": "mongodb", "value": 0.8381557666899502, "group":0},
{"source": "cassandra", "target": "nosql", "value": 0.9399455765993556, "group":0},
{"source": "cce", "target": "cse", "value": 1.1895701027007473, "group":0},
{"source": "cce", "target": "csr", "value": 0.1416139128650247, "group":0},
{"source": "cce", "target": "fresher", "value": 0.6517074815640311, "group":0},
{"source": "cce", "target": "kpo", "value": 0.4812251210674451, "group":0},
{"source": "cce", "target": "uk", "value": 2.32005210431835, "group":0},
{"source": "cce", "target": "voice", "value": 2.3294415513277027, "group":0},
{"source": "ccna", "target": "cisco", "value": 1.2065303616886385, "group":0},
{"source": "ccna", "target": "lan", "value": 0.21421187609461942, "group":0},
{"source": "ccna", "target": "network", "value": 0.1746863491132522, "group":0},
{"source": "ccna", "target": "routing", "value": 0.30834167918323796, "group":0},
{"source": "ccna", "target": "wan", "value": 0.6907701371521456, "group":0},
{"source": "chain", "target": "warehouse", "value": 0.43016655133740456, "group":0},
{"source": "cisco", "target": "network", "value": 0.13519454006045975, "group":0},
{"source": "cisco", "target": "routing", "value": 0.714837074329538, "group":0},
{"source": "cisco", "target": "vpn", "value": 0.6251241700334625, "group":0},
{"source": "cisco", "target": "wan", "value": 1.5698832358726154, "group":0},
{"source": "cms", "target": "drupal", "value": 0.6213766736772816, "group":0},
{"source": "cms", "target": "joomla", "value": 0.5845772901687701, "group":0},
{"source": "cms", "target": "php", "value": 0.511158600573485, "group":0},
{"source": "cms", "target": "wordpress", "value": 0.7602228484533594, "group":0},
{"source": "cocoa", "target": "ios", "value": 2.3388621842809556, "group":0},
{"source": "cocoa", "target": "iphone", "value": 2.2278503171544832, "group":0},
{"source": "cocoa", "target": "mobile", "value": 0.24597690415155138, "group":0},
{"source": "cocoa", "target": "objective", "value": 2.12989782501463, "group":0},
{"source": "cocoa", "target": "sdk", "value": 1.0597941110326627, "group":0},
{"source": "cocoa", "target": "swift", "value": 1.8565926684459446, "group":0},
{"source": "codeigniter", "target": "laravel", "value": 2.5950913946767917, "group":0},
{"source": "codeigniter", "target": "magento", "value": 0.3192269101104967, "group":0},
{"source": "codeigniter", "target": "php", "value": 1.4888686976514098, "group":0},
{"source": "coding", "target": "debugging", "value": 0.19533395028861805, "group":0},
{"source": "cold", "target": "sales", "value": 0.1183851521337432, "group":0},
{"source": "com", "target": "pl", "value": 0.5044293049679096, "group":0},
{"source": "com", "target": "salesforce", "value": 1.7871007281138163, "group":0},
{"source": "comp", "target": "spot", "value": 0.6632905781132649, "group":0},
{"source": "corel", "target": "graphic", "value": 2.0019556076755425, "group":0},
{"source": "corel", "target": "illustrator", "value": 2.348314106758556, "group":0},
{"source": "corel", "target": "photoshop", "value": 2.493919184140303, "group":0},
{"source": "cse", "target": "csr", "value": 2.3864367755863976, "group":0},
{"source": "cse", "target": "voice", "value": 1.3240146505232748, "group":0},
{"source": "csr", "target": "voice", "value": 0.7229663803831043, "group":0},
{"source": "css", "target": "html", "value": 2.829839125556578, "group":0},
{"source": "css", "target": "javascript", "value": 2.6679347108913665, "group":0},
{"source": "css", "target": "jquery", "value": 2.3960467114735327, "group":0},
{"source": "css", "target": "mvc", "value": 0.1309502977105322, "group":0},
{"source": "css", "target": "php", "value": 0.6102084544610503, "group":0},
{"source": "css", "target": "ui", "value": 1.0702186909582807, "group":0},
{"source": "css", "target": "web", "value": 1.2409612440668445, "group":0},
{"source": "css", "target": "wordpress", "value": 0.27394544700614065, "group":0},
{"source": "cv", "target": "email", "value": 0.3056428555688723, "group":0},
{"source": "cvs", "target": "flex", "value": 0.11425201674477277, "group":0},
{"source": "data", "target": "mining", "value": 0.5524851538949186, "group":0},
{"source": "data", "target": "modeling", "value": 1.0086957158378855, "group":0},
{"source": "data", "target": "structures", "value": 2.086541429827729, "group":0},
{"source": "data", "target": "warehousing", "value": 0.6176415829855306, "group":0},
{"source": "database", "target": "dba", "value": 0.1724299764091833, "group":0},
{"source": "database", "target": "sql", "value": 0.7476802850555525, "group":0},
{"source": "dba", "target": "oracle", "value": 0.13732723964214233, "group":0},
{"source": "design", "target": "graphic", "value": 1.2998903943089248, "group":0},
{"source": "design", "target": "illustrator", "value": 0.5737733231092303, "group":0},
{"source": "design", "target": "photoshop", "value": 0.8974048997590915, "group":0},
{"source": "design", "target": "web", "value": 0.43640171770386127, "group":0},
{"source": "desktop", "target": "hardware", "value": 0.6326565446917902, "group":0},
{"source": "desktop", "target": "troubleshooting", "value": 0.18150053253288562, "group":0},
{"source": "devops", "target": "docker", "value": 1.4691137628296906, "group":0},
{"source": "devops", "target": "jenkins", "value": 1.825451194999495, "group":0},
{"source": "django", "target": "postgresql", "value": 0.10403830537196024, "group":0},
{"source": "django", "target": "python", "value": 0.9351558994499132, "group":0},
{"source": "dns", "target": "vpn", "value": 0.23605681107596627, "group":0},
{"source": "dns", "target": "windows", "value": 0.46176002813353645, "group":0},
{"source": "docker", "target": "jenkins", "value": 1.5222334423120294, "group":0},
{"source": "dot", "target": "net", "value": 1.3179535559804108, "group":0},
{"source": "dreamweaver", "target": "illustrator", "value": 0.15684313358556634, "group":0},
{"source": "dreamweaver", "target": "photoshop", "value": 1.4173846651444546, "group":0},
{"source": "drupal", "target": "joomla", "value": 2.376858652309196, "group":0},
{"source": "drupal", "target": "mysql", "value": 0.40261440056640785, "group":0},
{"source": "drupal", "target": "php", "value": 1.2820060276325767, "group":0},
{"source": "drupal", "target": "wordpress", "value": 1.8723189837053265, "group":0},
{"source": "e", "target": "e-commerce", "value": 2.8520412245408626, "group":0},
{"source": "e", "target": "suite", "value": 0.35848255483110236, "group":0},
{"source": "eclipse", "target": "tomcat", "value": 0.1437679336384629, "group":0},
{"source": "ejb", "target": "hibernate", "value": 0.27653899140605576, "group":0},
{"source": "ejb", "target": "j2ee", "value": 0.5882025617007872, "group":0},
{"source": "ejb", "target": "jdbc", "value": 0.40563530376217505, "group":0},
{"source": "ejb", "target": "jsp", "value": 1.6757915379139388, "group":0},
{"source": "ejb", "target": "servlets", "value": 1.0754569632843087, "group":0},
{"source": "ejb", "target": "struts", "value": 0.9544102696699065, "group":0},
{"source": "embedded", "target": "firmware", "value": 1.5088211280590402, "group":0},
{"source": "embedded", "target": "systems", "value": 0.1163151581984171, "group":0},
{"source": "erp", "target": "resources", "value": 1.5289730284709662, "group":0},
{"source": "erp", "target": "tally", "value": 0.8789016290035873, "group":0},
{"source": "etl", "target": "ssis", "value": 0.4239725982732442, "group":0},
{"source": "etl", "target": "warehousing", "value": 1.7719376898421586, "group":0},
{"source": "facebook", "target": "social", "value": 0.455357248001538, "group":0},
{"source": "fico", "target": "sap", "value": 1.3983373023124572, "group":0},
{"source": "firewall", "target": "routing", "value": 0.1225457885638826, "group":0},
{"source": "firewall", "target": "vpn", "value": 0.6139188568906548, "group":0},
{"source": "fresher", "target": "voice", "value": 1.8487685343841147, "group":0},
{"source": "gaap", "target": "ifrs", "value": 2.7532810995752515, "group":0},
{"source": "git", "target": "jenkins", "value": 0.5630762971972598, "group":0},
{"source": "git", "target": "svn", "value": 1.1727777218218183, "group":0},
{"source": "google", "target": "ppc", "value": 1.7568748764631976, "group":0},
{"source": "google", "target": "sem", "value": 2.1918171743518173, "group":0},
{"source": "google", "target": "seo", "value": 1.654186380582794, "group":0},
{"source": "google", "target": "social", "value": 0.19069219750384658, "group":0},
{"source": "graphic", "target": "graphics", "value": 1.7493808469158107, "group":0},
{"source": "graphic", "target": "illustrator", "value": 2.503886110205908, "group":0},
{"source": "graphic", "target": "photoshop", "value": 2.357797422684977, "group":0},
{"source": "graphics", "target": "illustrator", "value": 1.4822618723608099, "group":0},
{"source": "graphics", "target": "photoshop", "value": 1.3119125260080844, "group":0},
{"source": "gst", "target": "returns", "value": 0.9020691914031445, "group":0},
{"source": "gst", "target": "tally", "value": 1.0442862947400098, "group":0},
{"source": "gst", "target": "tds", "value": 2.7641094657381218, "group":0},
{"source": "hadoop", "target": "hive", "value": 2.5239193842060694, "group":0},
{"source": "hadoop", "target": "scala", "value": 1.0912764014326135, "group":0},
{"source": "hadoop", "target": "spark", "value": 2.5339859524077184, "group":0},
{"source": "hardware", "target": "networking", "value": 0.31104946662281674, "group":0},
{"source": "hibernate", "target": "j2ee", "value": 2.255190552646715, "group":0},
{"source": "hibernate", "target": "java", "value": 2.5440859555316706, "group":0},
{"source": "hibernate", "target": "jboss", "value": 0.5385265258075631, "group":0},
{"source": "hibernate", "target": "jdbc", "value": 0.22384029853193801, "group":0},
{"source": "hibernate", "target": "jsp", "value": 1.3857439187456833, "group":0},
{"source": "hibernate", "target": "maven", "value": 0.37294996205140696, "group":0},
{"source": "hibernate", "target": "servlets", "value": 0.4911038579729867, "group":0},
{"source": "hibernate", "target": "spring", "value": 2.818793168761107, "group":0},
{"source": "hibernate", "target": "struts", "value": 2.405688565632446, "group":0},
{"source": "hibernate", "target": "tomcat", "value": 0.6749894741050332, "group":0},
{"source": "hive", "target": "scala", "value": 0.8561150041636947, "group":0},
{"source": "hive", "target": "spark", "value": 2.4740842059419843, "group":0},
{"source": "hr", "target": "resources", "value": 0.9447511620981123, "group":0},
{"source": "hr", "target": "sourcing", "value": 0.4585533303617113, "group":0},
{"source": "html", "target": "javascript", "value": 2.8409217701983733, "group":0},
{"source": "html", "target": "jquery", "value": 2.444577290530229, "group":0},
{"source": "html", "target": "mysql", "value": 0.81603911433523, "group":0},
{"source": "html", "target": "net", "value": 1.4046653820144288, "group":0},
{"source": "html", "target": "oracle", "value": 0.34143532692497947, "group":0},
{"source": "html", "target": "php", "value": 1.49549746673515, "group":0},
{"source": "html", "target": "pmp", "value": 1.212221377196701, "group":0},
{"source": "html", "target": "python", "value": 0.5281783840536823, "group":0},
{"source": "html", "target": "sixsigma", "value": 1.293909160398006, "group":0},
{"source": "html", "target": "sql", "value": 0.21660702246431562, "group":0},
{"source": "html", "target": "ui", "value": 0.41475834820948276, "group":0},
{"source": "html", "target": "web", "value": 1.2642986861808878, "group":0},
{"source": "html", "target": "wordpress", "value": 0.2949366073603954, "group":0},
{"source": "html", "target": "xhtml", "value": 0.27136048824272807, "group":0},
{"source": "html", "target": "xml", "value": 0.4779539862987332, "group":0},
{"source": "ibm", "target": "wipro", "value": 2.2920698482858226, "group":0},
{"source": "illustrator", "target": "photoshop", "value": 2.93091839765639, "group":0},
{"source": "illustrator", "target": "ux", "value": 0.1330689005404361, "group":0},
{"source": "internet", "target": "online", "value": 0.7771415360685923, "group":0},
{"source": "internet", "target": "seo", "value": 0.3758723383036293, "group":0},
{"source": "ios", "target": "iphone", "value": 1.6116155135454757, "group":0},
{"source": "ios", "target": "mobile", "value": 1.5357349993726526, "group":0},
{"source": "ios", "target": "objective", "value": 2.6261030415115916, "group":0},
{"source": "ios", "target": "sdk", "value": 1.1342390555552344, "group":0},
{"source": "ios", "target": "swift", "value": 2.367312236329868, "group":0},
{"source": "iphone", "target": "objective", "value": 1.668565925622581, "group":0},
{"source": "iphone", "target": "sdk", "value": 0.7270512950016361, "group":0},
{"source": "iphone", "target": "swift", "value": 0.3330380573709336, "group":0},
{"source": "ites", "target": "kpo", "value": 1.3732337751268704, "group":0},
{"source": "j2ee", "target": "java", "value": 2.79681083330727, "group":0},
{"source": "j2ee", "target": "jboss", "value": 0.4649773765748553, "group":0},
{"source": "j2ee", "target": "jdbc", "value": 0.29228215972585403, "group":0},
{"source": "j2ee", "target": "jms", "value": 0.2023545535283419, "group":0},
{"source": "j2ee", "target": "jsp", "value": 0.9208817923405845, "group":0},
{"source": "j2ee", "target": "junit", "value": 0.34425303102322335, "group":0},
{"source": "j2ee", "target": "maven", "value": 0.11014620062015021, "group":0},
{"source": "j2ee", "target": "rest", "value": 0.2636568420238091, "group":0},
{"source": "j2ee", "target": "servlets", "value": 0.8248417981532956, "group":0},
{"source": "j2ee", "target": "spring", "value": 2.6469495220833, "group":0},
{"source": "j2ee", "target": "struts", "value": 1.3423189891036567, "group":0},
{"source": "java", "target": "javascript", "value": 0.321970851564334, "group":0},
{"source": "java", "target": "jboss", "value": 0.24847755432589513, "group":0},
{"source": "java", "target": "jdbc", "value": 0.44583234256095805, "group":0},
{"source": "java", "target": "jsp", "value": 1.2179312947434244, "group":0},
{"source": "java", "target": "junit", "value": 0.2611059425279, "group":0},
{"source": "java", "target": "maven", "value": 0.6028244575482843, "group":0},
{"source": "java", "target": "rest", "value": 1.1179943592115662, "group":0},
{"source": "java", "target": "servlets", "value": 0.47144416708325065, "group":0},
{"source": "java", "target": "spring", "value": 2.7210106033381845, "group":0},
{"source": "java", "target": "struts", "value": 1.2351750884678343, "group":0},
{"source": "java", "target": "tomcat", "value": 0.3386269505186623, "group":0},
{"source": "java", "target": "web", "value": 0.1394670227346478, "group":0},
{"source": "javascript", "target": "jquery", "value": 2.699674592647991, "group":0},
{"source": "javascript", "target": "json", "value": 0.2687840866940362, "group":0},
{"source": "javascript", "target": "mvc", "value": 0.6671772865733264, "group":0},
{"source": "javascript", "target": "mysql", "value": 1.5976124002495886, "group":0},
{"source": "javascript", "target": "net", "value": 1.5493263930443777, "group":0},
{"source": "javascript", "target": "node.js", "value": 1.7947200398101784, "group":0},
{"source": "javascript", "target": "php", "value": 1.2584352746093552, "group":0},
{"source": "javascript", "target": "pmp", "value": 0.6710769042784026, "group":0},
{"source": "javascript", "target": "python", "value": 0.7027437539497255, "group":0},
{"source": "javascript", "target": "react.js", "value": 1.4366224497680975, "group":0},
{"source": "javascript", "target": "sixsigma", "value": 0.6868053272186175, "group":0},
{"source": "javascript", "target": "sql", "value": 0.5247518157984139, "group":0},
{"source": "javascript", "target": "ui", "value": 0.4521717459118928, "group":0},
{"source": "javascript", "target": "web", "value": 1.462572334024889, "group":0},
{"source": "javascript", "target": "xhtml", "value": 0.10606752318456523, "group":0},
{"source": "javascript", "target": "xml", "value": 0.28437142406051674, "group":0},
{"source": "jboss", "target": "struts", "value": 0.24100041076098644, "group":0},
{"source": "jboss", "target": "tomcat", "value": 2.0523701647703483, "group":0},
{"source": "jboss", "target": "weblogic", "value": 1.1783566319063794, "group":0},
{"source": "jboss", "target": "websphere", "value": 0.2535037991070278, "group":0},
{"source": "jdbc", "target": "jms", "value": 0.49441866849384264, "group":0},
{"source": "jdbc", "target": "jsp", "value": 1.3300958762787871, "group":0},
{"source": "jdbc", "target": "servlets", "value": 0.47469368025309067, "group":0},
{"source": "jdbc", "target": "spring", "value": 0.2000065883511308, "group":0},
{"source": "jdbc", "target": "struts", "value": 0.2335972783726177, "group":0},
{"source": "joomla", "target": "magento", "value": 0.545482697376739, "group":0},
{"source": "joomla", "target": "mysql", "value": 0.39063046087671993, "group":0},
{"source": "joomla", "target": "php", "value": 1.0546076888141684, "group":0},
{"source": "joomla", "target": "wordpress", "value": 2.615731530065953, "group":0},
{"source": "jquery", "target": "json", "value": 0.5350657011950172, "group":0},
{"source": "jquery", "target": "mvc", "value": 1.3670097462178767, "group":0},
{"source": "jquery", "target": "mysql", "value": 1.2294080872849673, "group":0},
{"source": "jquery", "target": "net", "value": 0.3936115608262988, "group":0},
{"source": "jquery", "target": "php", "value": 1.5021482524957595, "group":0},
{"source": "jquery", "target": "sql", "value": 0.2190101240309738, "group":0},
{"source": "jquery", "target": "wcf", "value": 0.3302574791792946, "group":0},
{"source": "jquery", "target": "web", "value": 1.1561515573402297, "group":0},
{"source": "jquery", "target": "wordpress", "value": 0.3876592295226221, "group":0},
{"source": "jquery", "target": "xml", "value": 0.22870261203037134, "group":0},
{"source": "json", "target": "rest", "value": 0.352762419792667, "group":0},
{"source": "json", "target": "sdk", "value": 0.7814063870949225, "group":0},
{"source": "json", "target": "sqlite", "value": 0.3274861057784516, "group":0},
{"source": "json", "target": "xml", "value": 1.9443924126626313, "group":0},
{"source": "jsp", "target": "servlets", "value": 2.5745876867843855, "group":0},
{"source": "jsp", "target": "spring", "value": 0.7728908033510337, "group":0},
{"source": "jsp", "target": "struts", "value": 2.0693991436203723, "group":0},
{"source": "junit", "target": "maven", "value": 0.8606421562758386, "group":0},
{"source": "junit", "target": "spring", "value": 0.8426232693071009, "group":0},
{"source": "kpo", "target": "voice", "value": 1.0036784490990625, "group":0},
{"source": "lan", "target": "wan", "value": 2.8631976108431347, "group":0},
{"source": "laravel", "target": "php", "value": 1.7270472788897657, "group":0},
{"source": "laravel", "target": "zend", "value": 0.19300922602737036, "group":0},
{"source": "linq", "target": "mvc", "value": 0.7188949884141407, "group":0},
{"source": "linq", "target": "net", "value": 0.8337030532368285, "group":0},
{"source": "linq", "target": "wcf", "value": 0.9641336469764156, "group":0},
{"source": "linq", "target": "wpf", "value": 0.23852451282791123, "group":0},
{"source": "linux", "target": "perl", "value": 0.6828536423416313, "group":0},
{"source": "linux", "target": "scripting", "value": 0.5560038351708183, "group":0},
{"source": "linux", "target": "shell", "value": 0.517932671541605, "group":0},
{"source": "linux", "target": "unix", "value": 2.010288534584214, "group":0},
{"source": "linux", "target": "windows", "value": 0.9788401549238213, "group":0},
{"source": "machine", "target": "mining", "value": 0.22142120721684466, "group":0},
{"source": "machine", "target": "python", "value": 0.18838283924217356, "group":0},
{"source": "machine", "target": "r", "value": 0.3642407504831834, "group":0},
{"source": "magento", "target": "php", "value": 0.5213365908112582, "group":0},
{"source": "magento", "target": "wordpress", "value": 0.5991507818776176, "group":0},
{"source": "maven", "target": "spring", "value": 0.8072946146373452, "group":0},
{"source": "microservices", "target": "spring", "value": 0.36713420011351605, "group":0},
{"source": "mis", "target": "resources", "value": 1.7049347757171083, "group":0},
{"source": "mm", "target": "sap", "value": 1.6399018816896174, "group":0},
{"source": "mobile", "target": "sdk", "value": 0.6947481157355467, "group":0},
{"source": "modeling", "target": "sas", "value": 0.16793961467699992, "group":0},
{"source": "modeling", "target": "statistics", "value": 0.44267837159753465, "group":0},
{"source": "mongodb", "target": "node.js", "value": 0.4977444887679723, "group":0},
{"source": "mongodb", "target": "nosql", "value": 1.2879477266880015, "group":0},
{"source": "ms", "target": "office", "value": 2.710324911103033, "group":0},
{"source": "ms", "target": "powerpoint", "value": 0.2118246585871017, "group":0},
{"source": "ms", "target": "sql", "value": 0.20944534369415796, "group":0},
{"source": "ms", "target": "word", "value": 0.9690195703060497, "group":0},
{"source": "mvc", "target": "net", "value": 2.2007807041236362, "group":0},
{"source": "mvc", "target": "server", "value": 0.25856348749734426, "group":0},
{"source": "mvc", "target": "sql", "value": 0.5316163332523953, "group":0},
{"source": "mvc", "target": "wcf", "value": 1.3794784764158463, "group":0},
{"source": "mysql", "target": "php", "value": 2.742488579498453, "group":0},
{"source": "mysql", "target": "wordpress", "value": 0.3247239066969815, "group":0},
{"source": "mysql", "target": "zend", "value": 0.33582787092599825, "group":0},
{"source": "net", "target": "oracle", "value": 0.9256240597221127, "group":0},
{"source": "net", "target": "pmp", "value": 1.8881499386637945, "group":0},
{"source": "net", "target": "python", "value": 0.8029440635507472, "group":0},
{"source": "net", "target": "server", "value": 1.734467130117716, "group":0},
{"source": "net", "target": "sixsigma", "value": 1.9688988405298724, "group":0},
{"source": "net", "target": "sql", "value": 2.26436456964088, "group":0},
{"source": "net", "target": "vb", "value": 1.1233913128005621, "group":0},
{"source": "net", "target": "vb.net", "value": 1.4495543687189303, "group":0},
{"source": "net", "target": "wcf", "value": 1.6613642329065523, "group":0},
{"source": "net", "target": "wpf", "value": 0.3029529661059861, "group":0},
{"source": "network", "target": "networking", "value": 1.200858185646168, "group":0},
{"source": "network", "target": "routing", "value": 0.1860811258508141, "group":0},
{"source": "network", "target": "security", "value": 1.1288061917361418, "group":0},
{"source": "network", "target": "wan", "value": 0.15904773642444334, "group":0},
{"source": "node.js", "target": "react.js", "value": 1.9040862295725978, "group":0},
{"source": "objectoriented", "target": "programming", "value": 1.9936502659824733, "group":0},
{"source": "objective", "target": "swift", "value": 2.807783778360982, "group":0},
{"source": "online", "target": "seo", "value": 0.2311458876751503, "group":0},
{"source": "online", "target": "social", "value": 0.17695021609387468, "group":0},
{"source": "ooad", "target": "uml", "value": 0.28963649934111135, "group":0},
{"source": "oracle", "target": "plsql", "value": 0.9067489749433029, "group":0},
{"source": "oracle", "target": "pmp", "value": 1.9525341501893616, "group":0},
{"source": "oracle", "target": "python", "value": 1.1019104581072146, "group":0},
{"source": "oracle", "target": "sixsigma", "value": 2.027037510836863, "group":0},
{"source": "oracle", "target": "sql", "value": 1.27018157238433, "group":0},
{"source": "perl", "target": "scripting", "value": 0.7644315060486667, "group":0},
{"source": "perl", "target": "shell", "value": 0.42089099153019205, "group":0},
{"source": "perl", "target": "unix", "value": 0.5701958179457253, "group":0},
{"source": "perl", "target": "verilog", "value": 0.37880442088485833, "group":0},
{"source": "php", "target": "web", "value": 0.30027198121907794, "group":0},
{"source": "php", "target": "wordpress", "value": 2.112468961013467, "group":0},
{"source": "php", "target": "zend", "value": 1.1126152716293127, "group":0},
{"source": "pl", "target": "plsql", "value": 1.4301885797941583, "group":0},
{"source": "pmp", "target": "python", "value": 1.9853724181872558, "group":0},
{"source": "pmp", "target": "sixsigma", "value": 2.9195378293199568, "group":0},
{"source": "pmp", "target": "website", "value": 0.14592910873855514, "group":0},
{"source": "pmp", "target": "xhtml", "value": 0.7435270804898632, "group":0},
{"source": "powerpoint", "target": "word", "value": 0.6478719841503596, "group":0},
{"source": "ppc", "target": "sem", "value": 2.2187971764788528, "group":0},
{"source": "ppc", "target": "seo", "value": 1.5425194293653803, "group":0},
{"source": "pr", "target": "relations", "value": 1.0137296468380754, "group":0},
{"source": "profiling", "target": "sales", "value": 0.9936936879274982, "group":0},
{"source": "programming", "target": "software", "value": 0.27914114995865563, "group":0},
{"source": "protocols", "target": "routing", "value": 1.0649977593425546, "group":0},
{"source": "python", "target": "sixsigma", "value": 2.1037977773164998, "group":0},
{"source": "qa", "target": "qc", "value": 1.2467666177011378, "group":0},
{"source": "qa", "target": "selenium", "value": 0.15245579801617964, "group":0},
{"source": "queries", "target": "sql", "value": 0.43327896576141167, "group":0},
{"source": "r", "target": "sas", "value": 0.5809640196896746, "group":0},
{"source": "r", "target": "to", "value": 0.14809746192755557, "group":0},
{"source": "rest", "target": "soap", "value": 1.9201285573156972, "group":0},
{"source": "rest", "target": "spring", "value": 1.0391512093999757, "group":0},
{"source": "returns", "target": "tds", "value": 1.7122811828665336, "group":0},
{"source": "routing", "target": "vpn", "value": 0.9739217216553655, "group":0},
{"source": "routing", "target": "wan", "value": 0.28175195127483493, "group":0},
{"source": "sas", "target": "statistics", "value": 2.56438671111597, "group":0},
{"source": "sas", "target": "tableau", "value": 0.2560294489776904, "group":0},
{"source": "scala", "target": "spark", "value": 2.3106937400153473, "group":0},
{"source": "scripting", "target": "shell", "value": 2.976819920737083, "group":0},
{"source": "scripting", "target": "unix", "value": 1.6046023487516186, "group":0},
{"source": "sdk", "target": "sqlite", "value": 1.5561559652526349, "group":0},
{"source": "sem", "target": "seo", "value": 2.4543803332995533, "group":0},
{"source": "sem", "target": "social", "value": 0.48780002075885653, "group":0},
{"source": "seo", "target": "social", "value": 1.6470322897303729, "group":0},
{"source": "server", "target": "sql", "value": 2.513886140244179, "group":0},
{"source": "server", "target": "windows", "value": 0.26621621403236967, "group":0},
{"source": "servlets", "target": "spring", "value": 0.7686541422051756, "group":0},
{"source": "servlets", "target": "struts", "value": 0.8927560487269668, "group":0},
{"source": "sheet", "target": "statements", "value": 0.3613568792918266, "group":0},
{"source": "shell", "target": "unix", "value": 1.8961048734280963, "group":0},
{"source": "sixsigma", "target": "xhtml", "value": 0.5489781208169077, "group":0},
{"source": "soc", "target": "verilog", "value": 1.8409703012364953, "group":0},
{"source": "spring", "target": "struts", "value": 1.5837018449557556, "group":0},
{"source": "spring", "target": "tomcat", "value": 0.12673410902151855, "group":0},
{"source": "sql", "target": "wcf", "value": 0.4395348414996054, "group":0},
{"source": "sql", "target": "xml", "value": 0.15027301704664267, "group":0},
{"source": "ssis", "target": "ssrs", "value": 2.908194935072671, "group":0},
{"source": "ssrs", "target": "t", "value": 0.4682054110606132, "group":0},
{"source": "studio", "target": "visual", "value": 2.774973797045625, "group":0},
{"source": "system", "target": "verilog", "value": 0.16347893340955663, "group":0},
{"source": "tableau", "target": "visualization", "value": 0.4086662405326035, "group":0},
{"source": "tally", "target": "tds", "value": 1.6327950780612464, "group":0},
{"source": "tomcat", "target": "weblogic", "value": 0.8835044642100879, "group":0},
{"source": "troubleshooting", "target": "windows", "value": 0.11219570508844204, "group":0},
{"source": "ui", "target": "ux", "value": 1.6903148392707377, "group":0},
{"source": "uk", "target": "voice", "value": 1.7643937965483154, "group":0},
{"source": "vb", "target": "vb.net", "value": 2.965287400580543, "group":0},
{"source": "virtualization", "target": "vmware", "value": 0.9161552237008782, "group":0},
{"source": "vmware", "target": "windows", "value": 0.297599871430552, "group":0},
{"source": "vpn", "target": "wan", "value": 0.5666301557099613, "group":0},
{"source": "wan", "target": "wireless", "value": 0.5595342033327265, "group":0},
{"source": "wcf", "target": "wpf", "value": 2.301366355522895, "group":0},
{"source": "weblogic", "target": "websphere", "value": 0.3470800937942249, "group":0},
{"source": "website", "target": "xhtml", "value": 1.6976126880207798, "group":0},
{"source": "xhtml", "target": "xml", "value": 0.706761501493043, "group":0},
{"source": "xml", "target": "xslt", "value": 1.1072539909104007, "group":0}
    ]
    }
    
